spor_python-2.0.2.dist-info/METADATA
spor_python-2.0.2.dist-info/WHEEL
spor/__init__.py
spor/updating.py
spor/spor.cpython-38-darwin.so
spor_python-2.0.2.dist-info/RECORD
