Metadata-Version: 2.1
Name: spor-python
Version: 2.0.2
Classifier: Programming Language :: Python
Requires-Dist: pyyaml
Project-Url: https://github.com/abingham/spor-python
Summary: Python bindings for spor
Author: Austin Bingham <austin.bingham@gmail.com>
Author-Email: Austin Bingham <austin.bingham@gmail.com>
Maintainer: Austin Bingham
Maintainer-Email: austin.bingham@gmail.com
License: MIT
